csi_py/__init__.py
csi_py/csireader.py
csi_py-0.0.3.dist-info/licenses/LICENSE
csi_py-0.0.3.dist-info/METADATA
csi_py-0.0.3.dist-info/WHEEL
csi_py-0.0.3.dist-info/top_level.txt
csi_py-0.0.3.dist-info/RECORD
