Metadata-Version: 2.4
Name: csi_py
Version: 0.0.3
Summary: A python package for ingesting CSI data from ESP 32 modules
Author-email: Ryan Kuederle <ryan@rkuederle.com>
License-Expression: MIT
Project-URL: Homepage, https://github.com/kuederleR/csi_py
Project-URL: Issues, https://github.com/kuederleR/csi_py/issues
Classifier: Programming Language :: Python :: 3
Classifier: Operating System :: OS Independent
Requires-Python: >=3.6
License-File: LICENSE
Requires-Dist: numpy
Requires-Dist: pyserial
Dynamic: license-file
